adafruit_bno08x_rvc.py
adafruit_circuitpython_bno08x_rvc-1.0.21.dist-info/licenses/LICENSE
adafruit_circuitpython_bno08x_rvc-1.0.21.dist-info/METADATA
adafruit_circuitpython_bno08x_rvc-1.0.21.dist-info/WHEEL
adafruit_circuitpython_bno08x_rvc-1.0.21.dist-info/top_level.txt
adafruit_circuitpython_bno08x_rvc-1.0.21.dist-info/RECORD
