Metadata-Version: 2.4
Name: adafruit-circuitpython-bno08x-rvc
Version: 1.0.21
Summary: A simple helper library for using the UART-RVC mode of the BNO08x IMUs
Author-email: Adafruit Industries <circuitpython@adafruit.com>
License: MIT
Project-URL: Homepage, https://github.com/adafruit/Adafruit_CircuitPython_BNO08x_RVC
Keywords: adafruit,blinka,circuitpython,micropython,bno08x_rvc,IMU,RVC,UART,Hillcrest,Laboratories,Sensor,Fusion,Heading,AHRS
Classifier: Intended Audience :: Developers
Classifier: Topic :: Software Development :: Libraries
Classifier: Topic :: Software Development :: Embedded Systems
Classifier: Topic :: System :: Hardware
Classifier: License :: OSI Approved :: MIT License
Classifier: Programming Language :: Python :: 3
License-File: LICENSE
Requires-Dist: Adafruit-Blinka
Provides-Extra: optional
Dynamic: license-file
